LICENSE
MANIFEST.in
README.md
setup.py
business_settings/__init__.py
business_settings/admin.py
business_settings/apps.py
business_settings/models.py
business_settings/tests.py
business_settings/views.py
business_settings/migrations/__init__.py
customers/__init__.py
customers/admin.py
customers/apps.py
customers/forms.py
customers/models.py
customers/tests.py
customers/views.py
customers/migrations/__init__.py
django_invoiceproject.egg-info/PKG-INFO
django_invoiceproject.egg-info/SOURCES.txt
django_invoiceproject.egg-info/dependency_links.txt
django_invoiceproject.egg-info/top_level.txt
invoiceapp/__init__.py
invoiceapp/admin.py
invoiceapp/apps.py
invoiceapp/invoice.py
invoiceapp/models.py
invoiceapp/tests.py
invoiceapp/urls.py
invoiceapp/views.py
invoiceapp/migrations/__init__.py
invoiceproject/__init__.py
invoiceproject/settings.py
invoiceproject/urls.py
invoiceproject/wsgi.py
pets/__init__.py
pets/admin.py
pets/apps.py
pets/models.py
pets/tests.py
pets/views.py
pets/migrations/__init__.py
services/__init__.py
services/admin.py
services/apps.py
services/models.py
services/tests.py
services/views.py
services/migrations/__init__.py