Metadata-Version: 1.1
Name: django-invoiceproject
Version: 0.1.1a1
Summary: A simple Django project for generating and email pdf invoices.
Home-page: https://github.com/avezou/django_invoiceproject
Author: Avezou Petit Frere
Author-email: invoiceproject@apfware.com
License: MIT License
Platform: UNKNOWN
Classifier: Environment :: Web Environment
Classifier: Framework :: Django
Classifier: Framework :: Django :: 1.9
Classifier: Intended Audience :: Developers
Classifier: License :: OSI Approved :: MIT License
Classifier: Operating System :: OS Independent
Classifier: Programming Language :: Python
Classifier: Programming Language :: Python :: 3
Classifier: Programming Language :: Python :: 3.4
Classifier: Programming Language :: Python :: 3.5
Classifier: Topic :: Internet :: WWW/HTTP
Classifier: Topic :: Internet :: WWW/HTTP :: Dynamic Content
